minos/plugins/kong/__init__.py
minos/plugins/kong/client.py
minos/plugins/kong/discovery.py
minos/plugins/kong/middleware.py
minos/plugins/kong/utils.py
minos_discovery_kong-0.7.0.dist-info/LICENSE
minos_discovery_kong-0.7.0.dist-info/WHEEL
minos_discovery_kong-0.7.0.dist-info/METADATA
minos_discovery_kong-0.7.0.dist-info/RECORD
