Metadata-Version: 2.1
Name: minos-discovery-kong
Version: 0.7.0
Summary: The minos-kong plugin offer an interface that permit integrate Minos Microservice with Kong API Gateway
Home-page: https://www.minos.run/
License: MIT
Keywords: clariteia,minos,microservice,saga,kong
Author: Minos Framework Devs
Author-email: hey@minos.run
Requires-Python: >=3.9,<4.0
Classifier: Development Status :: 4 - Beta
Classifier: Intended Audience :: Developers
Classifier: License :: OSI Approved :: MIT License
Classifier: Natural Language :: English
Classifier: Programming Language :: Python :: 3
Classifier: Programming Language :: Python :: 3.10
Classifier: Programming Language :: Python :: 3.9
Requires-Dist: PyJWT (>=2.3.0,<3.0.0)
Requires-Dist: httpx (>=0.22.0,<0.23.0)
Requires-Dist: minos-microservice-common (>=0.7.0,<0.8.0)
Requires-Dist: minos-microservice-networks (>=0.7.0,<0.8.0)
Requires-Dist: pytz (>=2022.1,<2023.0)
Project-URL: Repository, https://github.com/minos-framework/minos-python
